hyssop/__init__.py
hyssop/__main__.py
hyssop/command.py
hyssop/pack.yaml
hyssop/project/__init__.py
hyssop/project/config_validator.py
hyssop/project/constants.py
hyssop/project/local.csv
hyssop/project/mixin.py
hyssop/project/pack.py
hyssop/project/component/__init__.py
hyssop/project/component/base.py
hyssop/project/component/config.py
hyssop/project/component/default.py
hyssop/project/component/mixin.py
hyssop/project/web/__init__.py
hyssop/project/web/app_mixin.py
hyssop/project/web/config.py
hyssop/project/web/controller.py
hyssop/unit_test/__init__.py
hyssop/unit_test/base.py
hyssop/unit_test/util.py
hyssop/unit_test/util_worker.py
hyssop/util/__init__.py
hyssop/util/callbacks.py
hyssop/util/constants.py
hyssop/util/dynamic_class_enum.py
hyssop/util/executor.py
hyssop/util/hierarchy_element.py
hyssop/util/local.csv
hyssop/util/localization.py
hyssop/util/logger.py
hyssop/util/utils.py
hyssop/util/worker.py
hyssop-1.1.7.dist-info/LICENSE
hyssop-1.1.7.dist-info/METADATA
hyssop-1.1.7.dist-info/WHEEL
hyssop-1.1.7.dist-info/top_level.txt
hyssop-1.1.7.dist-info/RECORD
