Metadata-Version: 2.1
Name: hyssop
Version: 1.1.7
Summary: component-based project hierarchy and utilities
Home-page: https://github.com/hsky77/hyssop
Author: hsky77
Author-email: howardlkung@gmail.com
License: MIT License
Platform: UNKNOWN
Classifier: Programming Language :: Python :: 3
Classifier: Programming Language :: Python :: 3.6
Classifier: Programming Language :: Python :: 3.7
Classifier: Programming Language :: Python :: 3.8
Classifier: License :: OSI Approved :: MIT License
Classifier: Operating System :: OS Independent
Requires-Python: >=3.6
License-File: LICENSE
Requires-Dist: PyYAML (>=5.1.1)
